{
    "id": 46620945,
    "action": "fp.upload",
    "timestamp": 1539002162,
    "text": {
        "container": "cde",
        "url": "https://cdn.filestackcontent.com/DhKzA9xuQFGzyKPwHXDX",
        "filename": "clock (3).jpg",
        "client": "Computer",
        "key": "ulafirstbucket/filestack",
        "type": "image/jpeg",
        "status": "Stored",
        "size": 909447
    }
}
{
    "id": 46622992,
    "action": "fp.upload",
    "timestamp": 1539003843,
    "text": {
        "client": "Computer",
        "filename": "clock (2).jpg",
        "size": 909447,
        "status": "Stored",
        "type": "image/jpeg",
        "url": "https://cdn.filestackcontent.com/Ntcn7IEYTfia8V7Q5DGO"
    }
}